pychek/__init__.py
pychek/main.py
pyprodigy/__init__.py
pyprodigy/main.py
pychek-0.0.2.4.dist-info/LICENSE
pychek-0.0.2.4.dist-info/METADATA
pychek-0.0.2.4.dist-info/WHEEL
pychek-0.0.2.4.dist-info/top_level.txt
pychek-0.0.2.4.dist-info/RECORD
